plockalyser/__init__.py
plockalyser/analyses.py
plockalyser/cli.py
plockalyser/dot.py
plockalyser/markdown.py
plockalyser-0.0.1.dist-info/METADATA
plockalyser-0.0.1.dist-info/WHEEL
plockalyser-0.0.1.dist-info/entry_points.txt
plockalyser-0.0.1.dist-info/licenses/LICENSE
plockalyser-0.0.1.dist-info/RECORD
