Metadata-Version: 2.4
Name: plockalyser
Version: 0.0.1
Summary: Utility for performing rudimentary analysis on npm package dependencies from an npm lock file.
Author-email: Rikard Gillemyr <rikard.gillemyr@gmail.com>
License: MIT
License-File: LICENSE
Classifier: License :: OSI Approved :: MIT License
Classifier: Operating System :: OS Independent
Classifier: Programming Language :: Python :: 3
Requires-Python: >=3.13
Requires-Dist: networkx
Requires-Dist: numpy
Requires-Dist: pydantic
Requires-Dist: ruff
Requires-Dist: scipy
